{
"meta":{"test_sets":[],"test_metrics":[],"learn_metrics":[{"best_value":"Min","name":"MultiClass"}],"launch_mode":"Train","parameters":"","iteration_count":100,"learn_sets":["learn"],"name":"experiment"},
"iterations":[
{"learn":[1.085384936],"iteration":0,"passed_time":0.003206849568,"remaining_time":0.3174781073},
{"learn":[1.073779361],"iteration":1,"passed_time":0.005980037383,"remaining_time":0.2930218318},
{"learn":[1.062992603],"iteration":2,"passed_time":0.009019091012,"remaining_time":0.2916172761},
{"learn":[1.053906883],"iteration":3,"passed_time":0.01181870782,"remaining_time":0.2836489876},
{"learn":[1.045387342],"iteration":4,"passed_time":0.01504272641,"remaining_time":0.2858118017},
{"learn":[1.038126249],"iteration":5,"passed_time":0.01792072896,"remaining_time":0.280758087},
{"learn":[1.031073608],"iteration":6,"passed_time":0.02218869784,"remaining_time":0.2947926999},
{"learn":[1.024896796],"iteration":7,"passed_time":0.02737378292,"remaining_time":0.3147985036},
{"learn":[1.019183507],"iteration":8,"passed_time":0.03011473821,"remaining_time":0.3044934641},
{"learn":[1.014113533],"iteration":9,"passed_time":0.03298562085,"remaining_time":0.2968705876},
{"learn":[1.009410029],"iteration":10,"passed_time":0.0370692103,"remaining_time":0.2999236106},
{"learn":[1.005102468],"iteration":11,"passed_time":0.04074776375,"remaining_time":0.2988169342},
{"learn":[1.001072957],"iteration":12,"passed_time":0.04355806847,"remaining_time":0.2915039967},
{"learn":[0.9976919074],"iteration":13,"passed_time":0.04636935143,"remaining_time":0.2848403016},
{"learn":[0.9946544146],"iteration":14,"passed_time":0.04912027907,"remaining_time":0.2783482481},
{"learn":[0.9916074996],"iteration":15,"passed_time":0.05271049843,"remaining_time":0.2767301168},
{"learn":[0.9888618978],"iteration":16,"passed_time":0.05670192704,"remaining_time":0.2768388203},
{"learn":[0.9866473032],"iteration":17,"passed_time":0.05968034499,"remaining_time":0.2718771272},
{"learn":[0.9843291703],"iteration":18,"passed_time":0.06228342114,"remaining_time":0.2655240586},
{"learn":[0.9821219972],"iteration":19,"passed_time":0.06526673981,"remaining_time":0.2610669593},
{"learn":[0.9802720709],"iteration":20,"passed_time":0.06814184587,"remaining_time":0.2563431345},
{"learn":[0.978422469],"iteration":21,"passed_time":0.07080626957,"remaining_time":0.2510404103},
{"learn":[0.9767930006],"iteration":22,"passed_time":0.07351255713,"remaining_time":0.2461072565},
{"learn":[0.9752013262],"iteration":23,"passed_time":0.07646754201,"remaining_time":0.2421472164},
{"learn":[0.9737801903],"iteration":24,"passed_time":0.07910705011,"remaining_time":0.2373211503},
{"learn":[0.9724261444],"iteration":25,"passed_time":0.08198199581,"remaining_time":0.2333333727},
{"learn":[0.9711284515],"iteration":26,"passed_time":0.08478996133,"remaining_time":0.2292469325},
{"learn":[0.9700356255],"iteration":27,"passed_time":0.08763181283,"remaining_time":0.2253389473},
{"learn":[0.9690746003],"iteration":28,"passed_time":0.09061004008,"remaining_time":0.221838374},
{"learn":[0.9681172962],"iteration":29,"passed_time":0.09388524923,"remaining_time":0.2190655815},
{"learn":[0.9670879306],"iteration":30,"passed_time":0.09696304367,"remaining_time":0.2158209682},
{"learn":[0.9662316061],"iteration":31,"passed_time":0.09962878031,"remaining_time":0.2117111582},
{"learn":[0.9654093744],"iteration":32,"passed_time":0.1021969042,"remaining_time":0.2074906842},
{"learn":[0.9646715766],"iteration":33,"passed_time":0.1055015269,"remaining_time":0.2047970816},
{"learn":[0.9640356237],"iteration":34,"passed_time":0.1084977344,"remaining_time":0.2014957925},
{"learn":[0.9634186266],"iteration":35,"passed_time":0.1109632021,"remaining_time":0.1972679148},
{"learn":[0.9628384793],"iteration":36,"passed_time":0.1135762809,"remaining_time":0.1933866405},
{"learn":[0.9618826259],"iteration":37,"passed_time":0.1159797596,"remaining_time":0.1892301341},
{"learn":[0.9613503912],"iteration":38,"passed_time":0.1184273772,"remaining_time":0.1852325643},
{"learn":[0.9607994555],"iteration":39,"passed_time":0.1212203789,"remaining_time":0.1818305684},
{"learn":[0.9601743173],"iteration":40,"passed_time":0.1240555454,"remaining_time":0.1785189556},
{"learn":[0.9596269085],"iteration":41,"passed_time":0.1268591575,"remaining_time":0.1751864556},
{"learn":[0.9590626134],"iteration":42,"passed_time":0.129257779,"remaining_time":0.171341707},
{"learn":[0.9584073257],"iteration":43,"passed_time":0.1317684081,"remaining_time":0.1677052467},
{"learn":[0.9578077195],"iteration":44,"passed_time":0.1342280627,"remaining_time":0.1640565211},
{"learn":[0.9572747962],"iteration":45,"passed_time":0.1367084037,"remaining_time":0.1604837782},
{"learn":[0.9568370548],"iteration":46,"passed_time":0.1390414444,"remaining_time":0.1567914161},
{"learn":[0.9562956533],"iteration":47,"passed_time":0.1415274882,"remaining_time":0.1533214455},
{"learn":[0.9559013818],"iteration":48,"passed_time":0.1439777815,"remaining_time":0.1498544257},
{"learn":[0.9554810689],"iteration":49,"passed_time":0.1462018783,"remaining_time":0.1462018783},
{"learn":[0.9550366968],"iteration":50,"passed_time":0.148556337,"remaining_time":0.1427305983},
{"learn":[0.9546945005],"iteration":51,"passed_time":0.151245416,"remaining_time":0.1396111532},
{"learn":[0.9542207674],"iteration":52,"passed_time":0.153985359,"remaining_time":0.1365530542},
{"learn":[0.9538644907],"iteration":53,"passed_time":0.1567915867,"remaining_time":0.1335632035},
{"learn":[0.9536192337],"iteration":54,"passed_time":0.1600365757,"remaining_time":0.1309390165},
{"learn":[0.9533495796],"iteration":55,"passed_time":0.1623422153,"remaining_time":0.1275545977},
{"learn":[0.9529497547],"iteration":56,"passed_time":0.1647386183,"remaining_time":0.1242765016},
{"learn":[0.9525471564],"iteration":57,"passed_time":0.1672113069,"remaining_time":0.1210840498},
{"learn":[0.9522717076],"iteration":58,"passed_time":0.169881704,"remaining_time":0.1180533875},
{"learn":[0.9519533675],"iteration":59,"passed_time":0.1724021702,"remaining_time":0.1149347801},
{"learn":[0.9517048177],"iteration":60,"passed_time":0.174798593,"remaining_time":0.1117564775},
{"learn":[0.9515245523],"iteration":61,"passed_time":0.1770693642,"remaining_time":0.1085263845},
{"learn":[0.9512849453],"iteration":62,"passed_time":0.1794592223,"remaining_time":0.1053966861},
{"learn":[0.9510130643],"iteration":63,"passed_time":0.1817490662,"remaining_time":0.1022338497},
{"learn":[0.9507999942],"iteration":64,"passed_time":0.1840303556,"remaining_time":0.0990932684},
{"learn":[0.9503265064],"iteration":65,"passed_time":0.186743123,"remaining_time":0.09620100274},
{"learn":[0.9499522838],"iteration":66,"passed_time":0.1894033272,"remaining_time":0.09328820593},
{"learn":[0.9496962319],"iteration":67,"passed_time":0.1917972146,"remaining_time":0.09025751276},
{"learn":[0.9493262778],"iteration":68,"passed_time":0.1945959157,"remaining_time":0.08742715052},
{"learn":[0.9490481188],"iteration":69,"passed_time":0.1970640833,"remaining_time":0.08445603571},
{"learn":[0.9487666742],"iteration":70,"passed_time":0.1999455035,"remaining_time":0.08166788172},
{"learn":[0.9484699732],"iteration":71,"passed_time":0.2027959343,"remaining_time":0.07886508555},
{"learn":[0.9481594128],"iteration":72,"passed_time":0.2051486992,"remaining_time":0.07587691615},
{"learn":[0.9479589087],"iteration":73,"passed_time":0.2074538675,"remaining_time":0.07288919667},
{"learn":[0.9477689406],"iteration":74,"passed_time":0.2097178834,"remaining_time":0.06990596114},
{"learn":[0.9474604906],"iteration":75,"passed_time":0.2120337958,"remaining_time":0.06695804077},
{"learn":[0.9471638627],"iteration":76,"passed_time":0.2143563931,"remaining_time":0.064028533},
{"learn":[0.9470620618],"iteration":77,"passed_time":0.2168410838,"remaining_time":0.06116030569},
{"learn":[0.9467741159],"iteration":78,"passed_time":0.219431231,"remaining_time":0.0583298209},
{"learn":[0.9466455545],"iteration":79,"passed_time":0.2218694172,"remaining_time":0.0554673543},
{"learn":[0.9463641403],"iteration":80,"passed_time":0.2248467226,"remaining_time":0.05274182383},
{"learn":[0.9461966718],"iteration":81,"passed_time":0.2273809645,"remaining_time":0.04991289464},
{"learn":[0.9459646069],"iteration":82,"passed_time":0.2301363621,"remaining_time":0.04713636333},
{"learn":[0.9456717358],"iteration":83,"passed_time":0.2328337598,"remaining_time":0.04434928757},
{"learn":[0.9452429654],"iteration":84,"passed_time":0.2353426345,"remaining_time":0.04153105314},
{"learn":[0.9449752869],"iteration":85,"passed_time":0.2376695615,"remaining_time":0.03869039373},
{"learn":[0.9447945917],"iteration":86,"passed_time":0.239895031,"remaining_time":0.03584638395},
{"learn":[0.9444453087],"iteration":87,"passed_time":0.2421475613,"remaining_time":0.03302012199},
{"learn":[0.9442586704],"iteration":88,"passed_time":0.2444035295,"remaining_time":0.0302071778},
{"learn":[0.9438979039],"iteration":89,"passed_time":0.2471502374,"remaining_time":0.02746113749},
{"learn":[0.943604925],"iteration":90,"passed_time":0.2495620347,"remaining_time":0.02468195947},
{"learn":[0.9434712445],"iteration":91,"passed_time":0.2518721039,"remaining_time":0.02190192208},
{"learn":[0.9429681333],"iteration":92,"passed_time":0.254225841,"remaining_time":0.01913527836},
{"learn":[0.9426943537],"iteration":93,"passed_time":0.2567175035,"remaining_time":0.01638622363},
{"learn":[0.9424781959],"iteration":94,"passed_time":0.2589679891,"remaining_time":0.01362989416},
{"learn":[0.942260723],"iteration":95,"passed_time":0.2614263648,"remaining_time":0.0108927652},
{"learn":[0.9420363787],"iteration":96,"passed_time":0.263997018,"remaining_time":0.008164856227},
{"learn":[0.9417773437],"iteration":97,"passed_time":0.2664050772,"remaining_time":0.00543683831},
{"learn":[0.9414805732],"iteration":98,"passed_time":0.26878822,"remaining_time":0.002715032525},
{"learn":[0.9412453257],"iteration":99,"passed_time":0.2710856311,"remaining_time":0}
]}